solvingerrors/__init__.py
solvingerrors/a.py
solvingerrors-1.1.0.dist-info/LICENSE
solvingerrors-1.1.0.dist-info/METADATA
solvingerrors-1.1.0.dist-info/WHEEL
solvingerrors-1.1.0.dist-info/top_level.txt
solvingerrors-1.1.0.dist-info/RECORD
