Metadata-Version: 2.1
Name: solvingerrors
Version: 1.1.0
Summary: An automated package that solves basic python errors
Home-page: https://github.com/pypa/pip
Author: Mani@pythonLovers
Author-email: maniscrow@proton.me
Classifier: Natural Language :: English
Classifier: Operating System :: OS Independent
Classifier: Intended Audience :: Developers
Classifier: License :: OSI Approved :: MIT License
Classifier: Programming Language :: Python :: 3
Requires-Python: >=3.6
License-File: LICENSE
Requires-Dist: keyboard
